statistically/__init__.py
statistically/__main__.py
statistically/statistically.py
test/__init__.py
test/conftest.py
test/test_log_regress.py
test/test_logs.py
test/test_stuff.py
statistically-0.1.3.dist-info/LICENSE
statistically-0.1.3.dist-info/METADATA
statistically-0.1.3.dist-info/WHEEL
statistically-0.1.3.dist-info/entry_points.txt
statistically-0.1.3.dist-info/top_level.txt
statistically-0.1.3.dist-info/zip-safe
statistically-0.1.3.dist-info/RECORD
