Metadata-Version: 2.1
Name: statistically
Version: 0.1.3
Summary: An empty-featured Stata output scraper/parser.
Home-page: https://github.com/vaneseltine/statistically
Author: Matt VanEseltine
Author-email: matvan@umich.edu
License: AGPL-3.0-or-later
Project-URL: Issue Tracker, https://github.com/vaneseltine/statistically/issues
Keywords: analysis,parsing,regression,stata,statistical,statistics
Platform: UNKNOWN
Classifier: Development Status :: 1 - Planning
Classifier: Environment :: Console
Classifier: Intended Audience :: Education
Classifier: Intended Audience :: End Users/Desktop
Classifier: Intended Audience :: Financial and Insurance Industry
Classifier: Intended Audience :: Science/Research
Classifier: License :: OSI Approved :: GNU Affero General Public License v3 or later (AGPLv3+)
Classifier: Natural Language :: English
Classifier: Operating System :: OS Independent
Classifier: Programming Language :: Python
Classifier: Programming Language :: Python :: 3.7
Classifier: Programming Language :: Python :: 3.8
Classifier: Programming Language :: Python :: 3.9
Classifier: Programming Language :: Python :: 3 :: Only
Classifier: Topic :: Office/Business
Classifier: Topic :: Scientific/Engineering
Classifier: Topic :: Scientific/Engineering :: Mathematics
Classifier: Topic :: Sociology
Classifier: Topic :: Text Processing
Classifier: Typing :: Typed
